{"gameTime":8,"state":{"npc_dota_hero_faceless_void":{"lastAbilityUpgraded":"","victory":true,"state":{"kills":0,"towersLeft":1,"netWorth":0.00839999970048666,"xp":0.012438271194696426,"teamXp":0.01649382710456848,"teamDeaths":0,"enemyTowersLeft":1,"deaths":0,"teamNetWorth":0.05454999953508377,"teamKills":0},"lastItemPurchased":[0,0,0,0,0,0,0,0,0,0,0]},"npc_dota_hero_earthshaker":{"lastAbilityUpgraded":"","victory":false,"state":{"kills":0,"towersLeft":1,"netWorth":0.008799999952316284,"xp":0.0029320986941456795,"teamXp":0.016382716596126556,"teamDeaths":0,"enemyTowersLeft":1,"deaths":0,"teamNetWorth":0.04805999994277954,"teamKills":0},"lastItemPurchased":[0,0,0,0,0,0,0,0,0,0,0]},"npc_dota_hero_drow_ranger":{"lastAbilityUpgraded":"","victory":true,"state":{"kills":0,"towersLeft":1,"netWorth":0.012480000033974648,"xp":0.029104938730597496,"teamXp":0.01649382710456848,"teamDeaths":0,"enemyTowersLeft":1,"deaths":0,"teamNetWorth":0.05454999953508377,"teamKills":0},"lastItemPurchased":[0,0,0,0,0,0,0,0,0,0,0]},"npc_dota_hero_invoker":{"lastAbilityUpgraded":"","victory":false,"state":{"kills":0,"towersLeft":1,"netWorth":0.010610000230371952,"xp":0.03123456798493862,"teamXp":0.016382716596126556,"teamDeaths":0,"enemyTowersLeft":1,"deaths":0,"teamNetWorth":0.04805999994277954,"teamKills":0},"lastItemPurchased":[0,0,1,0,0,0,0,0,0,0,0]},"npc_dota_hero_arc_warden":{"lastAbilityUpgraded":"","victory":true,"state":{"kills":0,"towersLeft":1,"netWorth":0.013980000279843807,"xp":0.01895061694085598,"teamXp":0.01649382710456848,"teamDeaths":0,"enemyTowersLeft":1,"deaths":0,"teamNetWorth":0.05454999953508377,"teamKills":0},"lastItemPurchased":[0,0,0,0,0,0,0,0,0,0,0]},"npc_dota_hero_mirana":{"lastAbilityUpgraded":"","victory":true,"state":{"kills":0,"towersLeft":1,"netWorth":0.011189999990165234,"xp":0.011358024552464485,"teamXp":0.01649382710456848,"teamDeaths":0,"enemyTowersLeft":1,"deaths":0,"teamNetWorth":0.05454999953508377,"teamKills":0},"lastItemPurchased":[0,0,0,0,0,0,0,0,0,0,0]},"npc_dota_hero_vengefulspirit":{"lastAbilityUpgraded":"","victory":false,"state":{"kills":0,"towersLeft":1,"netWorth":0.0062500000931322575,"xp":0.006604938302189112,"teamXp":0.016382716596126556,"teamDeaths":0,"enemyTowersLeft":1,"deaths":0,"teamNetWorth":0.04805999994277954,"teamKills":0},"lastItemPurchased":[0,0,0,0,0,0,0,0,0,0,0]},"npc_dota_hero_omniknight":{"lastAbilityUpgraded":"","victory":true,"state":{"kills":0,"towersLeft":1,"netWorth":0.008500000461935997,"xp":0.01061728410422802,"teamXp":0.01649382710456848,"teamDeaths":0,"enemyTowersLeft":1,"deaths":0,"teamNetWorth":0.05454999953508377,"teamKills":0},"lastItemPurchased":[0,0,0,1,0,0,0,0,0,0,0]},"npc_dota_hero_juggernaut":{"lastAbilityUpgraded":"","victory":false,"state":{"kills":0,"towersLeft":1,"netWorth":0.013849999755620956,"xp":0.02796296216547489,"teamXp":0.016382716596126556,"teamDeaths":0,"enemyTowersLeft":1,"deaths":0,"teamNetWorth":0.04805999994277954,"teamKills":0},"lastItemPurchased":[0,0,0,1,0,0,0,0,0,0,0]},"npc_dota_hero_magnataur":{"lastAbilityUpgraded":"","victory":false,"state":{"kills":0,"towersLeft":1,"netWorth":0.008550000376999378,"xp":0.013179012574255466,"teamXp":0.016382716596126556,"teamDeaths":0,"enemyTowersLeft":1,"deaths":0,"teamNetWorth":0.04805999994277954,"teamKills":0},"lastItemPurchased":[0,0,0,0,0,0,0,0,0,0,0]}}}