{"gameTime":7,"state":{"npc_dota_hero_antimage":{"lastAbilityUpgraded":"","victory":true,"state":{"kills":0,"towersLeft":1,"netWorth":0.008980000391602516,"xp":0.00932098738849163,"teamXp":0.015240740962326527,"teamDeaths":0,"enemyTowersLeft":1,"deaths":0,"teamNetWorth":0.05045999959111214,"teamKills":0.0020000000949949026},"lastItemPurchased":[0,0,0,0,0,0,0,0,0,0,0]},"npc_dota_hero_rubick":{"lastAbilityUpgraded":"","victory":false,"state":{"kills":0,"towersLeft":1,"netWorth":0.007249999791383743,"xp":0.007376543246209621,"teamXp":0.01174074038863182,"teamDeaths":0.0020000000949949026,"enemyTowersLeft":1,"deaths":0,"teamNetWorth":0.04267000034451485,"teamKills":0},"lastItemPurchased":[0,0,0,0,0,0,0,0,0,0,0]},"npc_dota_hero_drow_ranger":{"lastAbilityUpgraded":"","victory":false,"state":{"kills":0,"towersLeft":1,"netWorth":0.008469999767839909,"xp":0.01666666753590107,"teamXp":0.01174074038863182,"teamDeaths":0.0020000000949949026,"enemyTowersLeft":1,"deaths":0.0010000000474974513,"teamNetWorth":0.04267000034451485,"teamKills":0},"lastItemPurchased":[0,0,0,0,0,0,0,0,0,0,0]},"npc_dota_hero_axe":{"lastAbilityUpgraded":"","victory":false,"state":{"kills":0,"towersLeft":1,"netWorth":0.010619999840855598,"xp":0.012438271194696426,"teamXp":0.01174074038863182,"teamDeaths":0.0020000000949949026,"enemyTowersLeft":1,"deaths":0,"teamNetWorth":0.04267000034451485,"teamKills":0},"lastItemPurchased":[0,0,0,1,0,0,0,0,0,0,0]},"npc_dota_hero_pudge":{"lastAbilityUpgraded":"","victory":false,"state":{"kills":0,"towersLeft":1,"netWorth":0.005960000213235617,"xp":0.0013888889225199819,"teamXp":0.01174074038863182,"teamDeaths":0.0020000000949949026,"enemyTowersLeft":1,"deaths":0.0010000000474974513,"teamNetWorth":0.04267000034451485,"teamKills":0},"lastItemPurchased":[0,0,0,0,0,0,0,0,0,0,0]},"npc_dota_hero_mirana":{"lastAbilityUpgraded":"","victory":true,"state":{"kills":0.0010000000474974513,"towersLeft":1,"netWorth":0.014709999784827232,"xp":0.01993827149271965,"teamXp":0.015240740962326527,"teamDeaths":0,"enemyTowersLeft":1,"deaths":0,"teamNetWorth":0.05045999959111214,"teamKills":0.0020000000949949026},"lastItemPurchased":[0,0,0,0,0,0,0,0,0,0,0]},"npc_dota_hero_ember_spirit":{"lastAbilityUpgraded":"","victory":true,"state":{"kills":0.0010000000474974513,"towersLeft":1,"netWorth":0.010610000230371952,"xp":0.019320987164974213,"teamXp":0.015240740962326527,"teamDeaths":0,"enemyTowersLeft":1,"deaths":0,"teamNetWorth":0.05045999959111214,"teamKills":0.0020000000949949026},"lastItemPurchased":[0,0,0,0,0,0,0,0,0,0,0]},"npc_dota_hero_rattletrap":{"lastAbilityUpgraded":"","victory":true,"state":{"kills":0,"towersLeft":1,"netWorth":0.00913000013679266,"xp":0.017314814031124115,"teamXp":0.015240740962326527,"teamDeaths":0,"enemyTowersLeft":1,"deaths":0,"teamNetWorth":0.05045999959111214,"teamKills":0.0020000000949949026},"lastItemPurchased":[0,0,0,0,0,0,0,0,0,0,0]},"npc_dota_hero_obsidian_destroyer":{"lastAbilityUpgraded":"","victory":false,"state":{"kills":0,"towersLeft":1,"netWorth":0.010370000265538692,"xp":0.02083333395421505,"teamXp":0.01174074038863182,"teamDeaths":0.0020000000949949026,"enemyTowersLeft":1,"deaths":0,"teamNetWorth":0.04267000034451485,"teamKills":0},"lastItemPurchased":[0,0,0,0,0,0,0,0,0,0,0]},"npc_dota_hero_disruptor":{"lastAbilityUpgraded":"","victory":true,"state":{"kills":0,"towersLeft":1,"netWorth":0.007029999978840351,"xp":0.010308641940355301,"teamXp":0.015240740962326527,"teamDeaths":0,"enemyTowersLeft":1,"deaths":0,"teamNetWorth":0.05045999959111214,"teamKills":0.0020000000949949026},"lastItemPurchased":[0,0,0,0,0,0,0,0,0,0,0]}}}