{"gameTime":7,"state":{"npc_dota_hero_winter_wyvern":{"lastAbilityUpgraded":"","victory":true,"state":{"kills":0,"towersLeft":1,"netWorth":0.0062500000931322575,"xp":0.0073456792160868645,"teamXp":0.009549383074045181,"teamDeaths":0,"enemyTowersLeft":1,"deaths":0,"teamNetWorth":0.038589999079704285,"teamKills":0},"lastItemPurchased":[0,0,0,0,0,0,0,0,0,0,0]},"npc_dota_hero_rubick":{"lastAbilityUpgraded":"","victory":false,"state":{"kills":0,"towersLeft":1,"netWorth":0.0062500000931322575,"xp":0.006172839552164078,"teamXp":0.008697531186044216,"teamDeaths":0,"enemyTowersLeft":1,"deaths":0,"teamNetWorth":0.03711000084877014,"teamKills":0},"lastItemPurchased":[0,0,0,0,0,0,0,0,0,0,0]},"npc_dota_hero_mirana":{"lastAbilityUpgraded":"","victory":false,"state":{"kills":0,"towersLeft":1,"netWorth":0.008150000125169754,"xp":0.017993826419115067,"teamXp":0.008697531186044216,"teamDeaths":0,"enemyTowersLeft":1,"deaths":0,"teamNetWorth":0.03711000084877014,"teamKills":0},"lastItemPurchased":[0,0,0,0,0,0,0,0,0,0,0]},"npc_dota_hero_ember_spirit":{"lastAbilityUpgraded":"","victory":true,"state":{"kills":0,"towersLeft":1,"netWorth":0.007799999788403511,"xp":0.006635802332311869,"teamXp":0.009549383074045181,"teamDeaths":0,"enemyTowersLeft":1,"deaths":0,"teamNetWorth":0.038589999079704285,"teamKills":0},"lastItemPurchased":[0,0,0,0,0,0,0,0,0,0,0]},"npc_dota_hero_ogre_magi":{"lastAbilityUpgraded":"","victory":false,"state":{"kills":0,"towersLeft":1,"netWorth":0.0062500000931322575,"xp":0.0024074073880910873,"teamXp":0.008697531186044216,"teamDeaths":0,"enemyTowersLeft":1,"deaths":0,"teamNetWorth":0.03711000084877014,"teamKills":0},"lastItemPurchased":[0,0,0,0,0,0,0,0,0,0,0]},"npc_dota_hero_rattletrap":{"lastAbilityUpgraded":"","victory":true,"state":{"kills":0,"towersLeft":1,"netWorth":0.006649999879300594,"xp":0.010401234962046146,"teamXp":0.009549383074045181,"teamDeaths":0,"enemyTowersLeft":1,"deaths":0,"teamNetWorth":0.038589999079704285,"teamKills":0},"lastItemPurchased":[0,0,0,0,0,0,0,0,0,0,0]},"npc_dota_hero_elder_titan":{"lastAbilityUpgraded":"","victory":true,"state":{"kills":0,"towersLeft":1,"netWorth":0.0062500000931322575,"xp":0.002530864207074046,"teamXp":0.009549383074045181,"teamDeaths":0,"enemyTowersLeft":1,"deaths":0,"teamNetWorth":0.038589999079704285,"teamKills":0},"lastItemPurchased":[0,0,0,0,0,0,0,0,0,0,0]},"npc_dota_hero_morphling":{"lastAbilityUpgraded":"","victory":false,"state":{"kills":0,"towersLeft":1,"netWorth":0.008630000054836273,"xp":0.010740741156041622,"teamXp":0.008697531186044216,"teamDeaths":0,"enemyTowersLeft":1,"deaths":0,"teamNetWorth":0.03711000084877014,"teamKills":0},"lastItemPurchased":[0,0,0,1,0,0,0,0,0,0,0]},"npc_dota_hero_magnataur":{"lastAbilityUpgraded":"","victory":true,"state":{"kills":0,"towersLeft":1,"netWorth":0.011640000157058239,"xp":0.02083333395421505,"teamXp":0.009549383074045181,"teamDeaths":0,"enemyTowersLeft":1,"deaths":0,"teamNetWorth":0.038589999079704285,"teamKills":0},"lastItemPurchased":[1,0,0,0,0,0,0,0,0,0,0]},"npc_dota_hero_weaver":{"lastAbilityUpgraded":"","victory":false,"state":{"kills":0,"towersLeft":1,"netWorth":0.007829999551177025,"xp":0.006172839552164078,"teamXp":0.008697531186044216,"teamDeaths":0,"enemyTowersLeft":1,"deaths":0,"teamNetWorth":0.03711000084877014,"teamKills":0},"lastItemPurchased":[0,0,0,0,0,0,0,0,0,0,0]}}}