{"gameTime":5,"state":{"npc_dota_hero_antimage":{"lastAbilityUpgraded":"","victory":true,"state":{"kills":0,"towersLeft":1,"netWorth":0.007849999703466892,"xp":0.010370370000600815,"teamXp":0.012432098388671875,"teamDeaths":0,"enemyTowersLeft":1,"deaths":0,"teamNetWorth":0.037539999932050705,"teamKills":0},"lastItemPurchased":[0,0,0,0,0,0,0,0,0,0,0]},"npc_dota_hero_life_stealer":{"lastAbilityUpgraded":"","victory":false,"state":{"kills":0,"towersLeft":1,"netWorth":0.008059999905526638,"xp":0.00824074074625969,"teamXp":0.011456790380179882,"teamDeaths":0,"enemyTowersLeft":1,"deaths":0,"teamNetWorth":0.043150000274181366,"teamKills":0},"lastItemPurchased":[0,0,0,0,0,0,0,0,0,0,0]},"npc_dota_hero_pudge":{"lastAbilityUpgraded":"","victory":true,"state":{"kills":0,"towersLeft":1,"netWorth":0.0062500000931322575,"xp":0.009259259328246117,"teamXp":0.012432098388671875,"teamDeaths":0,"enemyTowersLeft":1,"deaths":0,"teamNetWorth":0.037539999932050705,"teamKills":0},"lastItemPurchased":[0,0,0,0,0,0,0,0,0,0,0]},"npc_dota_hero_legion_commander":{"lastAbilityUpgraded":"","victory":true,"state":{"kills":0,"towersLeft":1,"netWorth":0.008799999952316284,"xp":0.014475308358669281,"teamXp":0.012432098388671875,"teamDeaths":0,"enemyTowersLeft":1,"deaths":0,"teamNetWorth":0.037539999932050705,"teamKills":0},"lastItemPurchased":[0,0,0,0,0,0,0,0,0,0,0]},"npc_dota_hero_nevermore":{"lastAbilityUpgraded":"","victory":true,"state":{"kills":0,"towersLeft":1,"netWorth":0.0076299998909235,"xp":0.01805555634200573,"teamXp":0.012432098388671875,"teamDeaths":0,"enemyTowersLeft":1,"deaths":0,"teamNetWorth":0.037539999932050705,"teamKills":0},"lastItemPurchased":[0,0,0,0,0,0,0,0,0,0,0]},"npc_dota_hero_windrunner":{"lastAbilityUpgraded":"","victory":false,"state":{"kills":0,"towersLeft":1,"netWorth":0.010700000450015068,"xp":0.02083333395421505,"teamXp":0.011456790380179882,"teamDeaths":0,"enemyTowersLeft":1,"deaths":0,"teamNetWorth":0.043150000274181366,"teamKills":0},"lastItemPurchased":[0,0,0,0,0,0,0,0,0,0,0]},"npc_dota_hero_morphling":{"lastAbilityUpgraded":"","victory":true,"state":{"kills":0,"towersLeft":1,"netWorth":0.007009999826550484,"xp":0.009999999776482582,"teamXp":0.012432098388671875,"teamDeaths":0,"enemyTowersLeft":1,"deaths":0,"teamNetWorth":0.037539999932050705,"teamKills":0},"lastItemPurchased":[0,0,0,1,0,0,0,0,0,0,0]},"npc_dota_hero_disruptor":{"lastAbilityUpgraded":"","victory":false,"state":{"kills":0,"towersLeft":1,"netWorth":0.0062500000931322575,"xp":0.008209876716136932,"teamXp":0.011456790380179882,"teamDeaths":0,"enemyTowersLeft":1,"deaths":0,"teamNetWorth":0.043150000274181366,"teamKills":0},"lastItemPurchased":[0,0,0,0,0,0,0,0,0,0,0]},"npc_dota_hero_magnataur":{"lastAbilityUpgraded":"","victory":false,"state":{"kills":0,"towersLeft":1,"netWorth":0.007369999773800373,"xp":0.011790123768150806,"teamXp":0.011456790380179882,"teamDeaths":0,"enemyTowersLeft":1,"deaths":0,"teamNetWorth":0.043150000274181366,"teamKills":0},"lastItemPurchased":[0,0,0,0,0,0,0,0,0,0,0]},"npc_dota_hero_slark":{"lastAbilityUpgraded":"","victory":false,"state":{"kills":0,"towersLeft":1,"netWorth":0.010769999586045742,"xp":0.008209876716136932,"teamXp":0.011456790380179882,"teamDeaths":0,"enemyTowersLeft":1,"deaths":0,"teamNetWorth":0.043150000274181366,"teamKills":0},"lastItemPurchased":[0,1,0,0,0,0,0,0,0,0,0]}}}