{"gameTime":7,"state":{"npc_dota_hero_bloodseeker":{"lastAbilityUpgraded":"","victory":true,"state":{"kills":0,"towersLeft":1,"netWorth":0.01583000086247921,"xp":0.04015431925654411,"teamXp":0.02750617265701294,"teamDeaths":0,"enemyTowersLeft":1,"deaths":0,"teamNetWorth":0.061420001089572906,"teamKills":0.0010000000474974513},"lastItemPurchased":[0,0,0,0,0,0,0,0,0,0,0]},"npc_dota_hero_phoenix":{"lastAbilityUpgraded":"","victory":false,"state":{"kills":0,"towersLeft":1,"netWorth":0.0062500000931322575,"xp":0.014444444328546524,"teamXp":0.02532098814845085,"teamDeaths":0.0010000000474974513,"enemyTowersLeft":1,"deaths":0,"teamNetWorth":0.05375999957323074,"teamKills":0},"lastItemPurchased":[0,0,0,1,0,0,0,0,0,0,0]},"npc_dota_hero_alchemist":{"lastAbilityUpgraded":"","victory":false,"state":{"kills":0,"towersLeft":1,"netWorth":0.01606000028550625,"xp":0.03947530686855316,"teamXp":0.02532098814845085,"teamDeaths":0.0010000000474974513,"enemyTowersLeft":1,"deaths":0,"teamNetWorth":0.05375999957323074,"teamKills":0},"lastItemPurchased":[0,0,0,1,0,0,0,0,0,0,0]},"npc_dota_hero_legion_commander":{"lastAbilityUpgraded":"","victory":true,"state":{"kills":0,"towersLeft":1,"netWorth":0.011730000376701355,"xp":0.04024691507220268,"teamXp":0.02750617265701294,"teamDeaths":0,"enemyTowersLeft":1,"deaths":0,"teamNetWorth":0.061420001089572906,"teamKills":0.0010000000474974513},"lastItemPurchased":[0,0,0,0,0,0,0,0,0,0,0]},"npc_dota_hero_pudge":{"lastAbilityUpgraded":"","victory":true,"state":{"kills":0,"towersLeft":1,"netWorth":0.009100000374019146,"xp":0.01854938268661499,"teamXp":0.02750617265701294,"teamDeaths":0,"enemyTowersLeft":1,"deaths":0,"teamNetWorth":0.061420001089572906,"teamKills":0.0010000000474974513},"lastItemPurchased":[0,0,0,0,0,0,0,0,0,0,0]},"npc_dota_hero_phantom_assassin":{"lastAbilityUpgraded":"","victory":false,"state":{"kills":0,"towersLeft":1,"netWorth":0.011149999685585499,"xp":0.013827160932123661,"teamXp":0.02532098814845085,"teamDeaths":0.0010000000474974513,"enemyTowersLeft":1,"deaths":0,"teamNetWorth":0.05375999957323074,"teamKills":0},"lastItemPurchased":[0,0,0,0,0,0,0,0,0,0,0]},"npc_dota_hero_luna":{"lastAbilityUpgraded":"","victory":true,"state":{"kills":0.0010000000474974513,"towersLeft":1,"netWorth":0.01360000018030405,"xp":0.02342592552304268,"teamXp":0.02750617265701294,"teamDeaths":0,"enemyTowersLeft":1,"deaths":0,"teamNetWorth":0.061420001089572906,"teamKills":0.0010000000474974513},"lastItemPurchased":[0,0,0,0,0,0,0,0,0,0,0]},"npc_dota_hero_ogre_magi":{"lastAbilityUpgraded":"","victory":true,"state":{"kills":0,"towersLeft":1,"netWorth":0.01116000022739172,"xp":0.015154320746660233,"teamXp":0.02750617265701294,"teamDeaths":0,"enemyTowersLeft":1,"deaths":0,"teamNetWorth":0.061420001089572906,"teamKills":0.0010000000474974513},"lastItemPurchased":[0,0,0,1,0,0,0,0,0,0,0]},"npc_dota_hero_necrolyte":{"lastAbilityUpgraded":"","victory":false,"state":{"kills":0,"towersLeft":1,"netWorth":0.006570000201463699,"xp":0.019382715225219727,"teamXp":0.02532098814845085,"teamDeaths":0.0010000000474974513,"enemyTowersLeft":1,"deaths":0.0010000000474974513,"teamNetWorth":0.05375999957323074,"teamKills":0},"lastItemPurchased":[0,0,0,0,0,0,0,0,0,0,0]},"npc_dota_hero_weaver":{"lastAbilityUpgraded":"","victory":false,"state":{"kills":0,"towersLeft":1,"netWorth":0.013729999773204327,"xp":0.03947530686855316,"teamXp":0.02532098814845085,"teamDeaths":0.0010000000474974513,"enemyTowersLeft":1,"deaths":0,"teamNetWorth":0.05375999957323074,"teamKills":0},"lastItemPurchased":[0,0,0,1,0,0,0,0,0,0,0]}}}