{"gameTime":6,"state":{"npc_dota_hero_bloodseeker":{"lastAbilityUpgraded":"","victory":false,"state":{"kills":0,"towersLeft":1,"netWorth":0.010119999758899212,"xp":0.018487654626369476,"teamXp":0.021253086626529694,"teamDeaths":0.0010000000474974513,"enemyTowersLeft":1,"deaths":0,"teamNetWorth":0.048239998519420624,"teamKills":0},"lastItemPurchased":[0,0,0,1,0,0,0,0,0,0,0]},"npc_dota_hero_rubick":{"lastAbilityUpgraded":"","victory":false,"state":{"kills":0,"towersLeft":1,"netWorth":0.008249999955296516,"xp":0.005493827164173126,"teamXp":0.021253086626529694,"teamDeaths":0.0010000000474974513,"enemyTowersLeft":1,"deaths":0.0010000000474974513,"teamNetWorth":0.048239998519420624,"teamKills":0},"lastItemPurchased":[1,0,0,0,0,0,0,0,0,0,0]},"npc_dota_hero_alchemist":{"lastAbilityUpgraded":"","victory":false,"state":{"kills":0,"towersLeft":1,"netWorth":0.011800000444054604,"xp":0.02074074000120163,"teamXp":0.021253086626529694,"teamDeaths":0.0010000000474974513,"enemyTowersLeft":1,"deaths":0,"teamNetWorth":0.048239998519420624,"teamKills":0},"lastItemPurchased":[0,0,0,0,1,0,0,0,0,0,0]},"npc_dota_hero_phantom_assassin":{"lastAbilityUpgraded":"","victory":true,"state":{"kills":0,"towersLeft":1,"netWorth":0.00851999968290329,"xp":0.017839506268501282,"teamXp":0.020888889208436012,"teamDeaths":0.0010000000474974513,"enemyTowersLeft":1,"deaths":0,"teamNetWorth":0.049150001257658005,"teamKills":0.0010000000474974513},"lastItemPurchased":[0,0,1,0,0,0,0,0,0,0,0]},"npc_dota_hero_invoker":{"lastAbilityUpgraded":"","victory":true,"state":{"kills":0,"towersLeft":1,"netWorth":0.0024500000290572643,"xp":0.01645061746239662,"teamXp":0.020888889208436012,"teamDeaths":0.0010000000474974513,"enemyTowersLeft":1,"deaths":0,"teamNetWorth":0.049150001257658005,"teamKills":0.0010000000474974513},"lastItemPurchased":[0,0,0,0,0,0,0,0,0,0,0]},"npc_dota_hero_ember_spirit":{"lastAbilityUpgraded":"","victory":false,"state":{"kills":0,"towersLeft":1,"netWorth":0.008329999633133411,"xp":0.031697530299425125,"teamXp":0.021253086626529694,"teamDeaths":0.0010000000474974513,"enemyTowersLeft":1,"deaths":0,"teamNetWorth":0.048239998519420624,"teamKills":0},"lastItemPurchased":[0,0,0,0,0,0,0,0,0,0,0]},"npc_dota_hero_necrolyte":{"lastAbilityUpgraded":"","victory":true,"state":{"kills":0.0010000000474974513,"towersLeft":1,"netWorth":0.010320000350475311,"xp":0.011944444850087166,"teamXp":0.020888889208436012,"teamDeaths":0.0010000000474974513,"enemyTowersLeft":1,"deaths":0.0010000000474974513,"teamNetWorth":0.049150001257658005,"teamKills":0.0010000000474974513},"lastItemPurchased":[0,0,0,0,0,0,0,0,0,0,0]},"npc_dota_hero_juggernaut":{"lastAbilityUpgraded":"","victory":true,"state":{"kills":0,"towersLeft":1,"netWorth":0.013419999741017818,"xp":0.023487653583288193,"teamXp":0.020888889208436012,"teamDeaths":0.0010000000474974513,"enemyTowersLeft":1,"deaths":0,"teamNetWorth":0.049150001257658005,"teamKills":0.0010000000474974513},"lastItemPurchased":[0,0,0,1,0,0,0,0,0,0,0]},"npc_dota_hero_magnataur":{"lastAbilityUpgraded":"","victory":true,"state":{"kills":0,"towersLeft":1,"netWorth":0.014440000057220459,"xp":0.0347222238779068,"teamXp":0.020888889208436012,"teamDeaths":0.0010000000474974513,"enemyTowersLeft":1,"deaths":0,"teamNetWorth":0.049150001257658005,"teamKills":0.0010000000474974513},"lastItemPurchased":[1,0,0,0,0,0,0,0,0,0,0]},"npc_dota_hero_slark":{"lastAbilityUpgraded":"","victory":false,"state":{"kills":0,"towersLeft":1,"netWorth":0.009739999659359455,"xp":0.02984567917883396,"teamXp":0.021253086626529694,"teamDeaths":0.0010000000474974513,"enemyTowersLeft":1,"deaths":0,"teamNetWorth":0.048239998519420624,"teamKills":0},"lastItemPurchased":[0,0,0,0,0,1,0,0,0,0,0]}}}