{"gameTime":7,"state":{"npc_dota_hero_pudge":{"lastAbilityUpgraded":"","victory":false,"state":{"kills":0.0010000000474974513,"towersLeft":1,"netWorth":0.011149999685585499,"xp":0.008209876716136932,"teamXp":0.01625925861299038,"teamDeaths":0,"enemyTowersLeft":1,"deaths":0,"teamNetWorth":0.051419999450445175,"teamKills":0.0020000000949949026},"lastItemPurchased":[0,0,0,0,0,0,0,0,0,0,0]},"npc_dota_hero_sand_king":{"lastAbilityUpgraded":"","victory":false,"state":{"kills":0,"towersLeft":1,"netWorth":0.008410000242292881,"xp":0.01657407358288765,"teamXp":0.01625925861299038,"teamDeaths":0,"enemyTowersLeft":1,"deaths":0,"teamNetWorth":0.051419999450445175,"teamKills":0.0020000000949949026},"lastItemPurchased":[0,0,0,0,0,0,0,0,0,0,0]},"npc_dota_hero_arc_warden":{"lastAbilityUpgraded":"","victory":false,"state":{"kills":0.0010000000474974513,"towersLeft":1,"netWorth":0.012889999896287918,"xp":0.027716049924492836,"teamXp":0.01625925861299038,"teamDeaths":0,"enemyTowersLeft":1,"deaths":0,"teamNetWorth":0.051419999450445175,"teamKills":0.0020000000949949026},"lastItemPurchased":[0,0,0,0,0,1,0,0,0,0,0]},"npc_dota_hero_mirana":{"lastAbilityUpgraded":"","victory":true,"state":{"kills":0,"towersLeft":1,"netWorth":0.009829999879002571,"xp":0.01734567992389202,"teamXp":0.014814814552664757,"teamDeaths":0.0020000000949949026,"enemyTowersLeft":1,"deaths":0.0010000000474974513,"teamNetWorth":0.04535999894142151,"teamKills":0},"lastItemPurchased":[0,0,0,0,0,0,0,0,0,0,0]},"npc_dota_hero_dazzle":{"lastAbilityUpgraded":"","victory":true,"state":{"kills":0,"towersLeft":1,"netWorth":0.0065299998968839645,"xp":0.00746913580223918,"teamXp":0.014814814552664757,"teamDeaths":0.0020000000949949026,"enemyTowersLeft":1,"deaths":0.0010000000474974513,"teamNetWorth":0.04535999894142151,"teamKills":0},"lastItemPurchased":[0,0,0,0,0,0,0,0,0,0,0]},"npc_dota_hero_shadow_demon":{"lastAbilityUpgraded":"","victory":false,"state":{"kills":0,"towersLeft":1,"netWorth":0.006940000224858522,"xp":0.015061728656291962,"teamXp":0.01625925861299038,"teamDeaths":0,"enemyTowersLeft":1,"deaths":0,"teamNetWorth":0.051419999450445175,"teamKills":0.0020000000949949026},"lastItemPurchased":[0,0,0,1,0,0,0,0,0,0,0]},"npc_dota_hero_omniknight":{"lastAbilityUpgraded":"","victory":true,"state":{"kills":0,"towersLeft":1,"netWorth":0.006690000183880329,"xp":0.0031481480691581964,"teamXp":0.014814814552664757,"teamDeaths":0.0020000000949949026,"enemyTowersLeft":1,"deaths":0,"teamNetWorth":0.04535999894142151,"teamKills":0},"lastItemPurchased":[0,0,0,0,0,0,0,0,0,0,0]},"npc_dota_hero_weaver":{"lastAbilityUpgraded":"","victory":false,"state":{"kills":0,"towersLeft":1,"netWorth":0.012029999867081642,"xp":0.013734567910432816,"teamXp":0.01625925861299038,"teamDeaths":0,"enemyTowersLeft":1,"deaths":0,"teamNetWorth":0.051419999450445175,"teamKills":0.0020000000949949026},"lastItemPurchased":[0,0,1,0,0,0,0,0,0,0,0]},"npc_dota_hero_batrider":{"lastAbilityUpgraded":"","victory":true,"state":{"kills":0,"towersLeft":1,"netWorth":0.009770000353455544,"xp":0.025370370596647263,"teamXp":0.014814814552664757,"teamDeaths":0.0020000000949949026,"enemyTowersLeft":1,"deaths":0,"teamNetWorth":0.04535999894142151,"teamKills":0},"lastItemPurchased":[0,0,0,0,0,0,0,0,0,0,0]},"npc_dota_hero_slark":{"lastAbilityUpgraded":"","victory":true,"state":{"kills":0,"towersLeft":1,"netWorth":0.012539999559521675,"xp":0.02074074000120163,"teamXp":0.014814814552664757,"teamDeaths":0.0020000000949949026,"enemyTowersLeft":1,"deaths":0,"teamNetWorth":0.04535999894142151,"teamKills":0},"lastItemPurchased":[0,1,0,0,0,0,0,0,0,0,0]}}}