{"gameTime":7,"state":{"npc_dota_hero_crystal_maiden":{"lastAbilityUpgraded":"","victory":false,"state":{"kills":0,"towersLeft":1,"netWorth":0.007350000087171793,"xp":0.00824074074625969,"teamXp":0.010049383156001568,"teamDeaths":0,"enemyTowersLeft":1,"deaths":0,"teamNetWorth":0.04851999878883362,"teamKills":0.0010000000474974513},"lastItemPurchased":[0,0,0,0,0,0,0,0,0,0,0]},"npc_dota_hero_ursa":{"lastAbilityUpgraded":"","victory":false,"state":{"kills":0.0010000000474974513,"towersLeft":1,"netWorth":0.016580000519752502,"xp":0.01101851835846901,"teamXp":0.010049383156001568,"teamDeaths":0,"enemyTowersLeft":1,"deaths":0,"teamNetWorth":0.04851999878883362,"teamKills":0.0010000000474974513},"lastItemPurchased":[0,0,0,1,0,0,0,0,0,0,0]},"npc_dota_hero_templar_assassin":{"lastAbilityUpgraded":"","victory":false,"state":{"kills":0,"towersLeft":1,"netWorth":0.008740000426769257,"xp":0.01666666753590107,"teamXp":0.010049383156001568,"teamDeaths":0,"enemyTowersLeft":1,"deaths":0,"teamNetWorth":0.04851999878883362,"teamKills":0.0010000000474974513},"lastItemPurchased":[0,0,0,0,0,0,0,0,0,0,0]},"npc_dota_hero_undying":{"lastAbilityUpgraded":"","victory":true,"state":{"kills":0,"towersLeft":1,"netWorth":0.00773000018671155,"xp":0.006234568078070879,"teamXp":0.009382716380059719,"teamDeaths":0.0010000000474974513,"enemyTowersLeft":1,"deaths":0.0010000000474974513,"teamNetWorth":0.042739998549222946,"teamKills":0},"lastItemPurchased":[0,0,0,0,0,0,0,0,0,0,0]},"npc_dota_hero_axe":{"lastAbilityUpgraded":"","victory":true,"state":{"kills":0,"towersLeft":1,"netWorth":0.007770000025629997,"xp":0.008796296082437038,"teamXp":0.009382716380059719,"teamDeaths":0.0010000000474974513,"enemyTowersLeft":1,"deaths":0,"teamNetWorth":0.042739998549222946,"teamKills":0},"lastItemPurchased":[0,0,0,0,0,0,0,0,0,0,0]},"npc_dota_hero_invoker":{"lastAbilityUpgraded":"","victory":true,"state":{"kills":0,"towersLeft":1,"netWorth":0.008510000072419643,"xp":0.011790123768150806,"teamXp":0.009382716380059719,"teamDeaths":0.0010000000474974513,"enemyTowersLeft":1,"deaths":0,"teamNetWorth":0.042739998549222946,"teamKills":0},"lastItemPurchased":[1,0,0,0,0,0,0,0,0,0,0]},"npc_dota_hero_mirana":{"lastAbilityUpgraded":"","victory":false,"state":{"kills":0,"towersLeft":1,"netWorth":0.008729999884963036,"xp":0.009876543655991554,"teamXp":0.010049383156001568,"teamDeaths":0,"enemyTowersLeft":1,"deaths":0,"teamNetWorth":0.04851999878883362,"teamKills":0.0010000000474974513},"lastItemPurchased":[0,0,0,0,0,0,0,0,0,0,0]},"npc_dota_hero_shredder":{"lastAbilityUpgraded":"","victory":true,"state":{"kills":0,"towersLeft":1,"netWorth":0.009119999594986439,"xp":0.013888888992369175,"teamXp":0.009382716380059719,"teamDeaths":0.0010000000474974513,"enemyTowersLeft":1,"deaths":0,"teamNetWorth":0.042739998549222946,"teamKills":0},"lastItemPurchased":[0,0,1,0,0,0,0,0,0,0,0]},"npc_dota_hero_doom_bringer":{"lastAbilityUpgraded":"","victory":true,"state":{"kills":0,"towersLeft":1,"netWorth":0.009610000066459179,"xp":0.006203703582286835,"teamXp":0.009382716380059719,"teamDeaths":0.0010000000474974513,"enemyTowersLeft":1,"deaths":0,"teamNetWorth":0.042739998549222946,"teamKills":0},"lastItemPurchased":[0,0,0,0,0,0,0,0,0,0,0]},"npc_dota_hero_omniknight":{"lastAbilityUpgraded":"","victory":false,"state":{"kills":0,"towersLeft":1,"netWorth":0.007120000198483467,"xp":0.004444444552063942,"teamXp":0.010049383156001568,"teamDeaths":0,"enemyTowersLeft":1,"deaths":0,"teamNetWorth":0.04851999878883362,"teamKills":0.0010000000474974513},"lastItemPurchased":[0,0,0,0,0,0,0,0,0,0,0]}}}