{"gameTime":8,"state":{"npc_dota_hero_bloodseeker":{"lastAbilityUpgraded":"","victory":false,"state":{"kills":0,"towersLeft":1,"netWorth":0.009730000048875809,"xp":0.020493827760219574,"teamXp":0.01850000023841858,"teamDeaths":0,"enemyTowersLeft":1,"deaths":0,"teamNetWorth":0.046390000730752945,"teamKills":0},"lastItemPurchased":[0,0,0,0,0,0,0,0,0,0,0]},"npc_dota_hero_faceless_void":{"lastAbilityUpgraded":"","victory":false,"state":{"kills":0,"towersLeft":1,"netWorth":0.012149999849498272,"xp":0.023580247536301613,"teamXp":0.01850000023841858,"teamDeaths":0,"enemyTowersLeft":1,"deaths":0,"teamNetWorth":0.046390000730752945,"teamKills":0},"lastItemPurchased":[0,0,0,1,0,0,0,0,0,0,0]},"npc_dota_hero_nyx_assassin":{"lastAbilityUpgraded":"","victory":true,"state":{"kills":0,"towersLeft":1,"netWorth":0.008790000341832638,"xp":0.02222222276031971,"teamXp":0.011629629880189896,"teamDeaths":0,"enemyTowersLeft":1,"deaths":0,"teamNetWorth":0.04050999879837036,"teamKills":0},"lastItemPurchased":[0,0,0,0,0,0,0,0,0,0,0]},"npc_dota_hero_pudge":{"lastAbilityUpgraded":"","victory":false,"state":{"kills":0,"towersLeft":1,"netWorth":0.0062500000931322575,"xp":0.004043209832161665,"teamXp":0.01850000023841858,"teamDeaths":0,"enemyTowersLeft":1,"deaths":0,"teamNetWorth":0.046390000730752945,"teamKills":0},"lastItemPurchased":[0,0,0,0,0,0,0,0,0,0,0]},"npc_dota_hero_mirana":{"lastAbilityUpgraded":"","victory":true,"state":{"kills":0,"towersLeft":1,"netWorth":0.008630000054836273,"xp":0.01796296238899231,"teamXp":0.011629629880189896,"teamDeaths":0,"enemyTowersLeft":1,"deaths":0,"teamNetWorth":0.04050999879837036,"teamKills":0},"lastItemPurchased":[0,0,0,1,0,0,0,0,0,0,0]},"npc_dota_hero_rattletrap":{"lastAbilityUpgraded":"","victory":false,"state":{"kills":0,"towersLeft":1,"netWorth":0.006990000139921904,"xp":0.022191358730196953,"teamXp":0.01850000023841858,"teamDeaths":0,"enemyTowersLeft":1,"deaths":0,"teamNetWorth":0.046390000730752945,"teamKills":0},"lastItemPurchased":[0,0,0,0,0,0,0,0,0,0,0]},"npc_dota_hero_shadow_demon":{"lastAbilityUpgraded":"","victory":true,"state":{"kills":0,"towersLeft":1,"netWorth":0.0062500000931322575,"xp":0.003703703638166189,"teamXp":0.011629629880189896,"teamDeaths":0,"enemyTowersLeft":1,"deaths":0,"teamNetWorth":0.04050999879837036,"teamKills":0},"lastItemPurchased":[0,0,0,0,0,0,0,0,0,0,0]},"npc_dota_hero_obsidian_destroyer":{"lastAbilityUpgraded":"","victory":false,"state":{"kills":0,"towersLeft":1,"netWorth":0.011269999668002129,"xp":0.022191358730196953,"teamXp":0.01850000023841858,"teamDeaths":0,"enemyTowersLeft":1,"deaths":0,"teamNetWorth":0.046390000730752945,"teamKills":0},"lastItemPurchased":[1,0,0,0,0,0,0,0,0,0,0]},"npc_dota_hero_juggernaut":{"lastAbilityUpgraded":"","victory":true,"state":{"kills":0,"towersLeft":1,"netWorth":0.010590000078082085,"xp":0.007129629608243704,"teamXp":0.011629629880189896,"teamDeaths":0,"enemyTowersLeft":1,"deaths":0,"teamNetWorth":0.04050999879837036,"teamKills":0},"lastItemPurchased":[0,1,0,0,0,0,0,0,0,0,0]},"npc_dota_hero_disruptor":{"lastAbilityUpgraded":"","victory":true,"state":{"kills":0,"towersLeft":1,"netWorth":0.0062500000931322575,"xp":0.007129629608243704,"teamXp":0.011629629880189896,"teamDeaths":0,"enemyTowersLeft":1,"deaths":0,"teamNetWorth":0.04050999879837036,"teamKills":0},"lastItemPurchased":[0,0,0,0,0,0,0,0,0,0,0]}}}