{"gameTime":6,"state":{"npc_dota_hero_crystal_maiden":{"lastAbilityUpgraded":"","victory":false,"state":{"kills":0,"towersLeft":1,"netWorth":0.00795000046491623,"xp":0.008611110970377922,"teamXp":0.006709876470267773,"teamDeaths":0,"enemyTowersLeft":1,"deaths":0,"teamNetWorth":0.03782999888062477,"teamKills":0},"lastItemPurchased":[0,0,0,0,0,0,0,0,0,0,0]},"npc_dota_hero_rubick":{"lastAbilityUpgraded":"","victory":true,"state":{"kills":0,"towersLeft":1,"netWorth":0.010250000283122063,"xp":0.0013580246595665812,"teamXp":0.006993826944380999,"teamDeaths":0,"enemyTowersLeft":1,"deaths":0,"teamNetWorth":0.04579000174999237,"teamKills":0},"lastItemPurchased":[0,0,0,1,0,0,0,0,0,0,0]},"npc_dota_hero_sand_king":{"lastAbilityUpgraded":"","victory":false,"state":{"kills":0,"towersLeft":1,"netWorth":0.0062500000931322575,"xp":0,"teamXp":0.006709876470267773,"teamDeaths":0,"enemyTowersLeft":1,"deaths":0,"teamNetWorth":0.03782999888062477,"teamKills":0},"lastItemPurchased":[0,0,0,0,0,0,0,0,0,0,0]},"npc_dota_hero_arc_warden":{"lastAbilityUpgraded":"","victory":false,"state":{"kills":0,"towersLeft":1,"netWorth":0.00798999983817339,"xp":0.011049382388591766,"teamXp":0.006709876470267773,"teamDeaths":0,"enemyTowersLeft":1,"deaths":0,"teamNetWorth":0.03782999888062477,"teamKills":0},"lastItemPurchased":[0,0,0,0,0,0,0,0,0,0,0]},"npc_dota_hero_phantom_assassin":{"lastAbilityUpgraded":"","victory":false,"state":{"kills":0,"towersLeft":1,"netWorth":0.009390000253915787,"xp":0.013888888992369175,"teamXp":0.006709876470267773,"teamDeaths":0,"enemyTowersLeft":1,"deaths":0,"teamNetWorth":0.03782999888062477,"teamKills":0},"lastItemPurchased":[0,0,0,1,0,0,0,0,0,0,0]},"npc_dota_hero_spirit_breaker":{"lastAbilityUpgraded":"","victory":false,"state":{"kills":0,"towersLeft":1,"netWorth":0.0062500000931322575,"xp":0,"teamXp":0.006709876470267773,"teamDeaths":0,"enemyTowersLeft":1,"deaths":0,"teamNetWorth":0.03782999888062477,"teamKills":0},"lastItemPurchased":[0,0,0,0,0,0,0,0,0,0,0]},"npc_dota_hero_beastmaster":{"lastAbilityUpgraded":"","victory":true,"state":{"kills":0,"towersLeft":1,"netWorth":0.00865000020712614,"xp":0.011419753544032574,"teamXp":0.006993826944380999,"teamDeaths":0,"enemyTowersLeft":1,"deaths":0,"teamNetWorth":0.04579000174999237,"teamKills":0},"lastItemPurchased":[0,0,0,0,0,0,0,0,0,0,0]},"npc_dota_hero_sven":{"lastAbilityUpgraded":"","victory":true,"state":{"kills":0,"towersLeft":1,"netWorth":0.01104000024497509,"xp":0.009691357612609863,"teamXp":0.006993826944380999,"teamDeaths":0,"enemyTowersLeft":1,"deaths":0,"teamNetWorth":0.04579000174999237,"teamKills":0},"lastItemPurchased":[0,0,1,0,0,0,0,0,0,0,0]},"npc_dota_hero_shadow_demon":{"lastAbilityUpgraded":"","victory":true,"state":{"kills":0,"towersLeft":1,"netWorth":0.0062500000931322575,"xp":0,"teamXp":0.006993826944380999,"teamDeaths":0,"enemyTowersLeft":1,"deaths":0,"teamNetWorth":0.04579000174999237,"teamKills":0},"lastItemPurchased":[0,0,0,0,0,0,0,0,0,0,0]},"npc_dota_hero_obsidian_destroyer":{"lastAbilityUpgraded":"","victory":true,"state":{"kills":0,"towersLeft":1,"netWorth":0.009600000455975533,"xp":0.012500000186264515,"teamXp":0.006993826944380999,"teamDeaths":0,"enemyTowersLeft":1,"deaths":0,"teamNetWorth":0.04579000174999237,"teamKills":0},"lastItemPurchased":[0,0,0,0,0,0,0,0,0,0,0]}}}