{"gameTime":9,"state":{"npc_dota_hero_drow_ranger":{"lastAbilityUpgraded":"","victory":false,"state":{"kills":0,"towersLeft":1,"netWorth":0.0074800001457333565,"xp":0.02759259194135666,"teamXp":0.029999999329447746,"teamDeaths":0.003000000026077032,"enemyTowersLeft":1,"deaths":0.0020000000949949026,"teamNetWorth":0.05014999955892563,"teamKills":0},"lastItemPurchased":[0,0,0,1,0,0,0,0,0,0,0]},"npc_dota_hero_pudge":{"lastAbilityUpgraded":"","victory":false,"state":{"kills":0,"towersLeft":1,"netWorth":0.0067900000140070915,"xp":0.01493827160447836,"teamXp":0.029999999329447746,"teamDeaths":0.003000000026077032,"enemyTowersLeft":1,"deaths":0,"teamNetWorth":0.05014999955892563,"teamKills":0},"lastItemPurchased":[1,0,0,0,0,0,0,0,0,0,0]},"npc_dota_hero_invoker":{"lastAbilityUpgraded":"","victory":true,"state":{"kills":0,"towersLeft":1,"netWorth":0.01875000074505806,"xp":0.04441358149051666,"teamXp":0.031425926834344864,"teamDeaths":0,"enemyTowersLeft":1,"deaths":0,"teamNetWorth":0.07145000249147415,"teamKills":0.003000000026077032},"lastItemPurchased":[0,0,0,0,0,1,0,0,0,0,0]},"npc_dota_hero_spirit_breaker":{"lastAbilityUpgraded":"","victory":true,"state":{"kills":0,"towersLeft":1,"netWorth":0.012230000458657742,"xp":0.02558642067015171,"teamXp":0.031425926834344864,"teamDeaths":0,"enemyTowersLeft":1,"deaths":0,"teamNetWorth":0.07145000249147415,"teamKills":0.003000000026077032},"lastItemPurchased":[0,0,0,0,0,0,0,0,0,0,0]},"npc_dota_hero_mirana":{"lastAbilityUpgraded":"","victory":false,"state":{"kills":0,"towersLeft":1,"netWorth":0.013939999975264072,"xp":0.04024691507220268,"teamXp":0.029999999329447746,"teamDeaths":0.003000000026077032,"enemyTowersLeft":1,"deaths":0,"teamNetWorth":0.05014999955892563,"teamKills":0},"lastItemPurchased":[0,0,0,0,0,0,0,0,0,0,0]},"npc_dota_hero_luna":{"lastAbilityUpgraded":"","victory":false,"state":{"kills":0,"towersLeft":1,"netWorth":0.011250000447034836,"xp":0.030895061790943146,"teamXp":0.029999999329447746,"teamDeaths":0.003000000026077032,"enemyTowersLeft":1,"deaths":0,"teamNetWorth":0.05014999955892563,"teamKills":0},"lastItemPurchased":[0,0,0,0,0,0,0,0,0,0,0]},"npc_dota_hero_ancient_apparition":{"lastAbilityUpgraded":"","victory":true,"state":{"kills":0.0010000000474974513,"towersLeft":1,"netWorth":0.009689999744296074,"xp":0.01993827149271965,"teamXp":0.031425926834344864,"teamDeaths":0,"enemyTowersLeft":1,"deaths":0,"teamNetWorth":0.07145000249147415,"teamKills":0.003000000026077032},"lastItemPurchased":[0,0,0,0,0,0,0,0,0,0,0]},"npc_dota_hero_weaver":{"lastAbilityUpgraded":"","victory":true,"state":{"kills":0.0020000000949949026,"towersLeft":1,"netWorth":0.016140000894665718,"xp":0.02558642067015171,"teamXp":0.031425926834344864,"teamDeaths":0,"enemyTowersLeft":1,"deaths":0,"teamNetWorth":0.07145000249147415,"teamKills":0.003000000026077032},"lastItemPurchased":[0,0,0,1,0,0,0,0,0,0,0]},"npc_dota_hero_slark":{"lastAbilityUpgraded":"","victory":true,"state":{"kills":0,"towersLeft":1,"netWorth":0.014639999717473984,"xp":0.041604939848184586,"teamXp":0.031425926834344864,"teamDeaths":0,"enemyTowersLeft":1,"deaths":0,"teamNetWorth":0.07145000249147415,"teamKills":0.003000000026077032},"lastItemPurchased":[0,1,0,0,0,0,0,0,0,0,0]},"npc_dota_hero_queenofpain":{"lastAbilityUpgraded":"","victory":false,"state":{"kills":0,"towersLeft":1,"netWorth":0.010689999908208847,"xp":0.03632716089487076,"teamXp":0.029999999329447746,"teamDeaths":0.003000000026077032,"enemyTowersLeft":1,"deaths":0.0010000000474974513,"teamNetWorth":0.05014999955892563,"teamKills":0},"lastItemPurchased":[0,0,0,0,1,0,0,0,0,0,0]}}}