{"gameTime":7,"state":{"npc_dota_hero_warlock":{"lastAbilityUpgraded":"","victory":true,"state":{"kills":0,"towersLeft":1,"netWorth":0.010239999741315842,"xp":0.005092592444270849,"teamXp":0.0034012345131486654,"teamDeaths":0.0010000000474974513,"enemyTowersLeft":1,"deaths":0,"teamNetWorth":0.044520001858472824,"teamKills":0.003000000026077032},"lastItemPurchased":[0,0,0,1,0,0,0,0,0,0,0]},"npc_dota_hero_nyx_assassin":{"lastAbilityUpgraded":"","victory":true,"state":{"kills":0,"towersLeft":1,"netWorth":0.0062500000931322575,"xp":0.0013888889225199819,"teamXp":0.0034012345131486654,"teamDeaths":0.0010000000474974513,"enemyTowersLeft":1,"deaths":0,"teamNetWorth":0.044520001858472824,"teamKills":0.003000000026077032},"lastItemPurchased":[0,0,0,0,0,0,0,0,0,0,0]},"npc_dota_hero_alchemist":{"lastAbilityUpgraded":"","victory":true,"state":{"kills":0,"towersLeft":1,"netWorth":0.009739999659359455,"xp":0.0027777778450399637,"teamXp":0.0034012345131486654,"teamDeaths":0.0010000000474974513,"enemyTowersLeft":1,"deaths":0,"teamNetWorth":0.044520001858472824,"teamKills":0.003000000026077032},"lastItemPurchased":[0,0,0,0,0,1,0,0,0,0,0]},"npc_dota_hero_pudge":{"lastAbilityUpgraded":"","victory":true,"state":{"kills":0.0020000000949949026,"towersLeft":1,"netWorth":0.009239999577403069,"xp":0.0030246912501752377,"teamXp":0.0034012345131486654,"teamDeaths":0.0010000000474974513,"enemyTowersLeft":1,"deaths":0.0010000000474974513,"teamNetWorth":0.044520001858472824,"teamKills":0.003000000026077032},"lastItemPurchased":[0,0,0,0,0,0,0,0,0,0,0]},"npc_dota_hero_huskar":{"lastAbilityUpgraded":"","victory":false,"state":{"kills":0,"towersLeft":1,"netWorth":0.0066200001165270805,"xp":0.001049382728524506,"teamXp":9.75308648776263E-4,"teamDeaths":0.0020000000949949026,"enemyTowersLeft":1,"deaths":0,"teamNetWorth":0.03303999826312065,"teamKills":0},"lastItemPurchased":[0,0,0,0,0,0,0,0,0,0,0]},"npc_dota_hero_oracle":{"lastAbilityUpgraded":"","victory":false,"state":{"kills":0,"towersLeft":1,"netWorth":0.007249999791383743,"xp":0.001049382728524506,"teamXp":9.75308648776263E-4,"teamDeaths":0.0020000000949949026,"enemyTowersLeft":1,"deaths":0,"teamNetWorth":0.03303999826312065,"teamKills":0},"lastItemPurchased":[0,0,0,0,0,0,0,0,0,0,0]},"npc_dota_hero_ogre_magi":{"lastAbilityUpgraded":"","victory":false,"state":{"kills":0,"towersLeft":1,"netWorth":0.005960000213235617,"xp":0,"teamXp":9.75308648776263E-4,"teamDeaths":0.0020000000949949026,"enemyTowersLeft":1,"deaths":0.0010000000474974513,"teamNetWorth":0.03303999826312065,"teamKills":0},"lastItemPurchased":[0,0,0,0,0,0,0,0,0,0,0]},"npc_dota_hero_morphling":{"lastAbilityUpgraded":"","victory":true,"state":{"kills":0.0010000000474974513,"towersLeft":1,"netWorth":0.009050000458955765,"xp":0.0047222222201526165,"teamXp":0.0034012345131486654,"teamDeaths":0.0010000000474974513,"enemyTowersLeft":1,"deaths":0,"teamNetWorth":0.044520001858472824,"teamKills":0.003000000026077032},"lastItemPurchased":[0,0,0,1,0,0,0,0,0,0,0]},"npc_dota_hero_juggernaut":{"lastAbilityUpgraded":"","victory":false,"state":{"kills":0,"towersLeft":1,"netWorth":0.007249999791383743,"xp":0.0027777778450399637,"teamXp":9.75308648776263E-4,"teamDeaths":0.0020000000949949026,"enemyTowersLeft":1,"deaths":0,"teamNetWorth":0.03303999826312065,"teamKills":0},"lastItemPurchased":[1,0,0,0,0,0,0,0,0,0,0]},"npc_dota_hero_batrider":{"lastAbilityUpgraded":"","victory":false,"state":{"kills":0,"towersLeft":1,"netWorth":0.005960000213235617,"xp":0,"teamXp":9.75308648776263E-4,"teamDeaths":0.0020000000949949026,"enemyTowersLeft":1,"deaths":0.0010000000474974513,"teamNetWorth":0.03303999826312065,"teamKills":0},"lastItemPurchased":[0,0,0,0,0,0,0,0,0,0,0]}}}